LICENSE.txt
MANIFEST.in
README.md
setup.py
managedstate/__init__.py
managedstate/attributename.py
managedstate/constants.py
managedstate/keyquery.py
managedstate/methods.py
managedstate/state.py
managedstate.egg-info/PKG-INFO
managedstate.egg-info/SOURCES.txt
managedstate.egg-info/dependency_links.txt
managedstate.egg-info/requires.txt
managedstate.egg-info/top_level.txt
managedstate/extensions/__init__.py
managedstate/extensions/listeners/__init__.py
managedstate/extensions/listeners/constants.py
managedstate/extensions/listeners/listeners.py
managedstate/extensions/listeners/methods.py
managedstate/extensions/registrar/__init__.py
managedstate/extensions/registrar/constants.py
managedstate/extensions/registrar/partialquery.py
managedstate/extensions/registrar/registrar.py