Metadata-Version: 2.1
Name: managedstate
Version: 5.1.0
Summary: State management inspired by Redux
Home-page: https://github.com/immijimmi/managedstate
Download-URL: https://github.com/immijimmi/managedstate/archive/refs/tags/v5.1.0.tar.gz
Author: immijimmi
Author-email: immijimmi1@gmail.com
License: MIT
Keywords: state,managed,management,access,data
Classifier: Development Status :: 4 - Beta
Classifier: Intended Audience :: Developers
Classifier: Topic :: Software Development :: Libraries :: Application Frameworks
Classifier: License :: OSI Approved :: MIT License
Classifier: Programming Language :: Python :: 3.8
License-File: LICENSE.txt
